MANIFEST.in
README.rst
setup.py
XStatic_AdminLTE.egg-info/PKG-INFO
XStatic_AdminLTE.egg-info/SOURCES.txt
XStatic_AdminLTE.egg-info/dependency_links.txt
XStatic_AdminLTE.egg-info/namespace_packages.txt
XStatic_AdminLTE.egg-info/not-zip-safe
XStatic_AdminLTE.egg-info/pbr.json
XStatic_AdminLTE.egg-info/top_level.txt
xstatic/__init__.py
xstatic/pkg/__init__.py
xstatic/pkg/adminlte/__init__.py
xstatic/pkg/adminlte/data/AdminLTE.css
xstatic/pkg/adminlte/data/AdminLTE.min.css
xstatic/pkg/adminlte/data/skins/_all-skins.css
xstatic/pkg/adminlte/data/skins/_all-skins.min.css
xstatic/pkg/adminlte/data/skins/skin-black-light.css
xstatic/pkg/adminlte/data/skins/skin-black-light.min.css
xstatic/pkg/adminlte/data/skins/skin-black.css
xstatic/pkg/adminlte/data/skins/skin-black.min.css
xstatic/pkg/adminlte/data/skins/skin-blue-light.css
xstatic/pkg/adminlte/data/skins/skin-blue-light.min.css
xstatic/pkg/adminlte/data/skins/skin-blue.css
xstatic/pkg/adminlte/data/skins/skin-blue.min.css
xstatic/pkg/adminlte/data/skins/skin-green-light.css
xstatic/pkg/adminlte/data/skins/skin-green-light.min.css
xstatic/pkg/adminlte/data/skins/skin-green.css
xstatic/pkg/adminlte/data/skins/skin-green.min.css
xstatic/pkg/adminlte/data/skins/skin-purple-light.css
xstatic/pkg/adminlte/data/skins/skin-purple-light.min.css
xstatic/pkg/adminlte/data/skins/skin-purple.css
xstatic/pkg/adminlte/data/skins/skin-purple.min.css
xstatic/pkg/adminlte/data/skins/skin-red-light.css
xstatic/pkg/adminlte/data/skins/skin-red-light.min.css
xstatic/pkg/adminlte/data/skins/skin-red.css
xstatic/pkg/adminlte/data/skins/skin-red.min.css
xstatic/pkg/adminlte/data/skins/skin-yellow-light.css
xstatic/pkg/adminlte/data/skins/skin-yellow-light.min.css
xstatic/pkg/adminlte/data/skins/skin-yellow.css
xstatic/pkg/adminlte/data/skins/skin-yellow.min.css