Metadata-Version: 1.0
Name: XStatic-AdminLTE
Version: 2.1.0.1
Summary: AdminLTE 2.1.0 (XStatic packaging standard)
Home-page: https://github.com/almasaeed2010/AdminLTE
Author: Michael Kuty
Author-email: mail@majklk.cz
License: (same as AdminLTE)
Keywords: adminlte xstatic
Platform: any
